fcp_silence_detector/__init__.py
fcp_silence_detector/cli.py
fcp_silence_detector/detect_silence.py
fcp_silence_detector/place_markers.py
fcp_silence_detector-0.0.1.dist-info/licenses/LICENSE
fcp_silence_detector-0.0.1.dist-info/METADATA
fcp_silence_detector-0.0.1.dist-info/WHEEL
fcp_silence_detector-0.0.1.dist-info/entry_points.txt
fcp_silence_detector-0.0.1.dist-info/top_level.txt
fcp_silence_detector-0.0.1.dist-info/RECORD
