Metadata-Version: 2.4
Name: fcp-silence-detector
Version: 0.0.1
Summary: Read FCPXML, detect silences, place Markers in FCPXML
Author-email: Sugil Steve Lee <sugilmath@gmail.com>
License-Expression: GPL-3.0-or-later
Project-URL: Homepage, https://github.com/leesugil/fcp_silence_detector
Project-URL: Issues, https://github.com/leesugil/fcp_silence_detector/issues
Classifier: Programming Language :: Python :: 3
Classifier: Operating System :: OS Independent
Requires-Python: >=3.9
License-File: LICENSE
Dynamic: license-file
